dvc_azure/__init__.py
dvc_azure/_dvc_azure_version.py
dvc_azure/spec.py
dvc_azure/tests/__init__.py
dvc_azure/tests/benchmarks.py
dvc_azure/tests/cloud.py
dvc_azure/tests/conftest.py
dvc_azure/tests/fixtures.py
dvc_azure/tests/test_azure.py
dvc_azure/tests/test_dvc.py
dvc_azure-3.1.0.dist-info/LICENSE
dvc_azure-3.1.0.dist-info/METADATA
dvc_azure-3.1.0.dist-info/WHEEL
dvc_azure-3.1.0.dist-info/top_level.txt
dvc_azure-3.1.0.dist-info/RECORD
